<?xml version="1.0" encoding="UTF-8"?>
<objects serializationModel="Studio.02.03.00">
	<object class="AudioFile" id="{29f8817b-83ad-43f7-98eb-e7ed553b9d67}">
		<property name="assetPath">
			<value>BlastDoorOpening.wav</value>
		</property>
		<property name="isStreaming">
			<value>true</value>
		</property>
		<property name="frequencyInKHz">
			<value>44.0999985</value>
		</property>
		<property name="channelCount">
			<value>2</value>
		</property>
		<property name="length">
			<value>16.423809523809524</value>
		</property>
		<relationship name="masterAssetFolder">
			<destination>{d881eb7d-919b-4d35-93ba-6b376105ce0e}</destination>
		</relationship>
	</object>
</objects>
