<?xml version="1.0" encoding="UTF-8"?>
<objects serializationModel="Studio.02.03.00">
	<object class="AudioFile" id="{4afeeaf2-5bf0-45b3-8443-02995207d8e1}">
		<property name="assetPath">
			<value>FootStepsOnMetal2.mp3</value>
		</property>
		<property name="isStreaming">
			<value>true</value>
		</property>
		<property name="frequencyInKHz">
			<value>48</value>
		</property>
		<property name="channelCount">
			<value>2</value>
		</property>
		<property name="length">
			<value>13.656000000000001</value>
		</property>
		<relationship name="masterAssetFolder">
			<destination>{d881eb7d-919b-4d35-93ba-6b376105ce0e}</destination>
		</relationship>
	</object>
</objects>
