<?xml version="1.0" encoding="UTF-8"?>
<objects serializationModel="Studio.02.02.00">
	<object class="AudioFile" id="{61e3f8b7-3418-4198-8852-886a4aafe4ca}">
		<property name="assetPath">
			<value>HeartBeat.mp3</value>
		</property>
		<property name="isStreaming">
			<value>true</value>
		</property>
		<property name="frequencyInKHz">
			<value>48</value>
		</property>
		<property name="channelCount">
			<value>2</value>
		</property>
		<property name="length">
			<value>24.911999999999999</value>
		</property>
		<relationship name="masterAssetFolder">
			<destination>{d881eb7d-919b-4d35-93ba-6b376105ce0e}</destination>
		</relationship>
	</object>
</objects>
